quantguard/__init__.py
quantguard/cmdline.py
quantguard/common/enum.py
quantguard/config/__init__.py
quantguard/config/account.py
quantguard/config/settings.yml
quantguard/dao/balance.py
quantguard/dao/clickhouse.py
quantguard/dao/ledger.py
quantguard/dao/order.py
quantguard/dao/position.py
quantguard/dao/v1.sql
quantguard/exchange/exchange.py
quantguard/exchange/gate/ufutures.py
quantguard/exchange/okx/ufutures.py
quantguard/worker/__init__.py
quantguard/worker/bill_worker.py
quantguard/worker/summary.py
quantguard/worker/worker.py
quantguard-0.1.38.dist-info/METADATA
quantguard-0.1.38.dist-info/WHEEL
quantguard-0.1.38.dist-info/entry_points.txt
quantguard-0.1.38.dist-info/RECORD
