Metadata-Version: 2.1
Name: quantguard
Version: 0.1.38
Summary: 交易对账
Author: Your Name
Author-email: you@example.com
Requires-Python: >=3.10,<4.0
Classifier: Programming Language :: Python :: 3
Classifier: Programming Language :: Python :: 3.10
Classifier: Programming Language :: Python :: 3.11
Classifier: Programming Language :: Python :: 3.12
Requires-Dist: apache-superset (>=4.0.2,<5.0.0)
Requires-Dist: ccxt (>=4.3.73,<5.0.0)
Requires-Dist: click (>=8.1.7,<9.0.0)
Requires-Dist: clickhouse-driver (>=0.2.8,<0.3.0)
Requires-Dist: clickhouse-sqlalchemy (==0.2.0)
Requires-Dist: croniter (>=3.0.3,<4.0.0)
Requires-Dist: dynaconf (>=3.2.6,<4.0.0)
Requires-Dist: jinja2 (>=3.1.4,<4.0.0)
Requires-Dist: matplotlib (>=3.9.2,<4.0.0)
Requires-Dist: pydantic (>=2.8.2,<3.0.0)
Requires-Dist: pygments (>=2.18.0,<3.0.0)
Requires-Dist: schedule (>=1.2.2,<2.0.0)
Requires-Dist: toml (>=0.10.2,<0.11.0)
